qaviton_proxy/__init__.py
qaviton_proxy-2019.9.29.7.59.59.460885.dist-info/LICENSE
qaviton_proxy-2019.9.29.7.59.59.460885.dist-info/METADATA
qaviton_proxy-2019.9.29.7.59.59.460885.dist-info/WHEEL
qaviton_proxy-2019.9.29.7.59.59.460885.dist-info/top_level.txt
qaviton_proxy-2019.9.29.7.59.59.460885.dist-info/RECORD
