Metadata-Version: 2.1
Name: qaviton-proxy
Version: 2019.9.29.7.59.59.460885
Summary: qaviton proxy
Home-page: https://github.com/qaviton/qaviton_proxy
Author: yehonadav
Author-email: yonadav.barilan@gmail.com
License: apache-2.0
Platform: UNKNOWN
Classifier: Programming Language :: Python :: 3.6
Requires-Dist: requests (>=2.22.0)
Requires-Dist: flask (>=1.1.1)
